{
  "type": "pfm:furniture",
  "ingredients": [
    {
      "item": "minecraft:gray_wool"
    },
    {
      "item": "minecraft:gray_wool"
    },
    {
      "item": "minecraft:gray_wool"
    },
    {
      "item": "betterendforge:lucernia_stripped_log"
    },
    {
      "item": "betterendforge:lucernia_stripped_log"
    }
  ],
  "result": {
    "item": "pfm:basic_lamp",
    "tag": {
      "BlockEntityTag": {
        "color": "gray",
        "variant": "betterendforge:lucernia"
      }
    }
  }
}